setup.py
cdonut/__init__.py
cdonut/cdonut.py
cdonut.egg-info/PKG-INFO
cdonut.egg-info/SOURCES.txt
cdonut.egg-info/dependency_links.txt
cdonut.egg-info/requires.txt
cdonut.egg-info/top_level.txt